jieba3/__init__.py
jieba3/hmm.json
jieba3/model.base.json
jieba3/model.large.json
jieba3/model.small.json
jieba3/tok.py
jieba3-1.0.2.dist-info/LICENSE
jieba3-1.0.2.dist-info/WHEEL
jieba3-1.0.2.dist-info/METADATA
jieba3-1.0.2.dist-info/RECORD
