Metadata-Version: 2.1
Name: jieba3
Version: 1.0.2
Summary: “结巴 3”中文分词：做最好的 Modern Python 3 中文分词组件
Keywords: Chinese,NLP,Analysis,Tokenizer
Author-email: Shihong Yan <yansh97@foxmail.com>
Requires-Python: >=3.10,<4
Requires-Dist: pydantic
Requires-Dist: isort ; extra == "dev"
Requires-Dist: black ; extra == "dev"
Requires-Dist: flit ; extra == "dev"
Project-URL: Home, https://github.com/yansh97/jieba3
Provides-Extra: dev
